snowmad/__init__.py
snowmad/snowflake.py
snowmad/terraform.py
snowmad-0.0.4.dist-info/LICENSE
snowmad-0.0.4.dist-info/METADATA
snowmad-0.0.4.dist-info/WHEEL
snowmad-0.0.4.dist-info/top_level.txt
snowmad-0.0.4.dist-info/RECORD
