Metadata-Version: 2.1
Name: snowmad
Version: 0.0.4
Summary: A Snowflake object transcription library for capturing Snowflake objects
Home-page: https://github.com/PrestonBlackburn/snowmad
Author: Preston Blackburn
Author-email: prestonblckbrn@gmail.com
Classifier: Programming Language :: Python :: 3.0
Classifier: License :: OSI Approved :: MIT License
Classifier: Operating System :: OS Independent
Classifier: Development Status :: 2 - Pre-Alpha
License-File: LICENSE
